aimet_common/__init__.py
aimet_onnx/__init__.py
aimet_onnx/_encoding.py
aimet_onnx/batch_norm_fold.py
aimet_onnx/cross_layer_equalization.py
aimet_onnx/defs.py
aimet_onnx/layer_output_utils.py
aimet_onnx/lite_mp.py
aimet_onnx/lpbq_utils.py
aimet_onnx/mixed_precision.py
aimet_onnx/qc_quantize_op.py
aimet_onnx/quant_analyzer.py
aimet_onnx/quantsim.py
aimet_onnx/utils.py
aimet_onnx/adaround/activation_sampler.py
aimet_onnx/adaround/adaround_loss.py
aimet_onnx/adaround/adaround_optimizer.py
aimet_onnx/adaround/adaround_tensor_quantizer.py
aimet_onnx/adaround/adaround_weight.py
aimet_onnx/adaround/utils.py
aimet_onnx/amp/mixed_precision_algo.py
aimet_onnx/amp/quantizer_groups.py
aimet_onnx/amp/utils.py
aimet_onnx/common/_libpymo.cpython-310-x86_64-linux-gnu.so
aimet_onnx/common/_version.py
aimet_onnx/common/aimet_tensor_quantizer.py
aimet_onnx/common/auto_quant.py
aimet_onnx/common/batch_norm_fold.py
aimet_onnx/common/bias_correction.py
aimet_onnx/common/bokeh_plots.py
aimet_onnx/common/cache.py
aimet_onnx/common/channel_pruner.py
aimet_onnx/common/comp_ratio_rounder.py
aimet_onnx/common/comp_ratio_select.py
aimet_onnx/common/compression_algo.py
aimet_onnx/common/cost_calculator.py
aimet_onnx/common/cross_layer_equalization.py
aimet_onnx/common/curve_fit.py
aimet_onnx/common/data_cache_utility.py
aimet_onnx/common/default_logging_config.json
aimet_onnx/common/defs.py
aimet_onnx/common/graph_pattern_matcher.py
aimet_onnx/common/graph_searcher.py
aimet_onnx/common/input_match_search.py
aimet_onnx/common/layer_database.py
aimet_onnx/common/layer_output_utils.py
aimet_onnx/common/layer_selector.py
aimet_onnx/common/libaimet_onnxrt_ops.so
aimet_onnx/common/libpymo.py
aimet_onnx/common/libquant_info.cpython-310-x86_64-linux-gnu.so
aimet_onnx/common/model_module.py
aimet_onnx/common/package_info.py.in
aimet_onnx/common/plotting_utils.py
aimet_onnx/common/polyslice.py
aimet_onnx/common/pruner.py
aimet_onnx-2.22.0.dist-info/METADATA
aimet_onnx-2.22.0.dist-info/WHEEL
aimet_onnx-2.22.0.dist-info/RECORD
aimet_onnx-2.22.0.dist-info/licenses/LICENSE
